DSCI_310_group_1_package/__init__.py
DSCI_310_group_1_package/DSCI_310_group_1_package.py
dsci_310_group_1_package-0.1.0.dist-info/LICENSE
dsci_310_group_1_package-0.1.0.dist-info/WHEEL
dsci_310_group_1_package-0.1.0.dist-info/METADATA
dsci_310_group_1_package-0.1.0.dist-info/RECORD
